{"programs":[{"kind":"manual","id":40662,"file":{"name":"151_korzo.mp3","metadata":{},"id":"0ff9951b-1562-4ffc-8945-18fdd3523fa2","duration":null},"fade_out_at":"2017-12-11T18:59:16+01:00","fade_in_at":"2017-12-11T18:00:00+01:00","cue_out_at":"2017-12-11T18:59:16+01:00","cue_in_at":"2017-12-11T18:00:00+01:00"},{"kind":"manual","id":38243,"file":{"name":"169_na_dobranicz_01_VII_2017.mp3","metadata":{},"id":"42fb5f33-59c6-4c28-a8bb-6eeb557b3c3b","duration":null},"fade_out_at":"2017-12-11T19:09:37+01:00","fade_in_at":"2017-12-11T19:00:00+01:00","cue_out_at":"2017-12-11T19:09:37+01:00","cue_in_at":"2017-12-11T19:00:00+01:00"},{"kind":"manual","id":40805,"file":{"name":"047_szczyro_donoszu_nenaleznewino-popowe-uzalani.mp3","metadata":{},"id":"788d8661-5904-4b25-9d3f-d8949b8eec23","duration":null},"fade_out_at":"2017-12-11T20:25:00+01:00","fade_in_at":"2017-12-11T20:00:00+01:00","cue_out_at":"2017-12-11T20:25:00+01:00","cue_in_at":"2017-12-11T20:00:00+01:00"}]}